[
    {
        "moneySpeed":1,
        "moneyUp":10,
        "thunderSpeed":0.1,
        
        "allVillageObject":["shoveler","shielder","projector","regeneration",
        "snowman","assassinFirst","freeze","wall",
        "iron","flyer","power","golder"],
        "villObjectHasLevel":{"shoveler":1,"shielder":1,"projector":1,"regeneration":1,
        "snowman":1,"assassinFirst":1,"freeze":1,"wall":1,
        "iron":1,"flyer":1,"power":1,"golder":1},
        "allMonsterObject":["zombie","creeper","s","sear","witch","ghost","spider","axer",
        null,null,null,null,null,null,null,null],
        "allVillageBuyObject":["freeze","wall","power","golder"],
        "villageBuyPrice":[1,2,3,4],
        "villageBuyLevel":[1,4,1,1],
        "Update":["card","gold"],
        "UpdatePrice":[[12,13,13],[13,14,14]],
        "UpdateLevel":[[1,1,1],[1,1,3]],

        "miniGame1":{
            "keepTime":30,
            "firstTime":10,
            "lastTime":10,
            "gunpowderRand":5,
            "timeRand":{"Min":1,"Max":3,"Cut":0.5}
        },
        "miniGame2":{
            "keepTime":30,
            "firstTime":10,
            "lastTime":10,
            "reloadTime":1,
            "fireworkSpeed":8,
            "mobSpeed":{"zombie":4,"ghost":2,"rand":0.5},
            "timeRand":{"zombie":{"Min":3,"Max":5},"ghost":{"Min":0.5,"Max":3}}  
        }
    },
    {
        "set":{"levelType":"defence","attackTime":0,"baseMonsterHealth":10,"baseVillageHealth":10,
        "thunderTime":0,"thunderTimeRand":0,
        "iceTime":0,"iceTimeRand":0},
        "groups":[
            {
                "firstCD":1,
                "firstCDNum":[],
                "soldier":["creeper","zombie","zombie"],
                "soldierCD":1.5,
                "groupCD":3,
                "groupCDRand":1,
                "groupTimes":4,
                "stopPos":null,
                "stopTime":null
            },
            {
                "firstCD":5,
                "firstCDNum":[],
                "soldier":["creeper","zombie"],
                "soldierCD":3,
                "groupCD":5,
                "groupCDRand":2,
                "groupTimes":3,
                "stopPos":null,
                "stopTime":null
            }
        ],"banCard":[],"chosenCard":["shoveler","projector",null,null,null,null]
    },
    {
        "set":{"levelType":"defence","attackTime":0,"baseMonsterHealth":10,"baseVillageHealth":10,
        "thunderTime":0,"thunderTimeRand":0,
        "iceTime":0,"iceTimeRand":0},
        "groups":[
            {
                "firstCD":5,
                "firstCDNum":[],
                "soldier":["zombie"],
                "soldierCD":0,
                "groupCD":10,
                "groupCDRand":2,
                "groupTimes":4,
                "stopPos":null,
                "stopTime":null
            },
            {
                "firstCD":7,
                "firstCDNum":[],
                "soldier":["axer"],
                "soldierCD":0,
                "groupCD":9,
                "groupCDRand":1,
                "groupTimes":3,
                "stopPos":null,
                "stopTime":null
            },
            {
                "firstCD":0.8,
                "firstCDNum":[],
                "soldier":["creeper","zombie","zombie","zombie"],
                "soldierCD":1.7,
                "groupCD":3,
                "groupCDRand":2,
                "groupTimes":4,
                "stopPos":null,
                "stopTime":null
            },
            {
                "firstCD":0,
                "firstCDNum":[3,3],
                "soldier":["creeper","zombie","zombie","zombie","axer","axer"],
                "soldierCD":1,
                "groupCD":0,
                "groupCDRand":0,
                "groupTimes":1,
                "stopPos":null,
                "stopTime":null
            }
        ],"banCard":[],"chosenCard":["shoveler","projector","regeneration",null,null,null]
    },
    {
        "set":{"levelType":"normal","attackTime":0,"baseMonsterHealth":20,"baseVillageHealth":20,
        "thunderTime":0,"thunderTimeRand":0,
        "iceTime":0,"iceTimeRand":0},
        "groups":[
            {
                "firstCD":0.8,
                "firstCDNum":[],
                "soldier":["creeper","zombie","skeleton","axer"],
                "soldierCD":2.6,
                "groupCD":4,
                "groupCDRand":1,
                "groupTimes":0,
                "stopPos":null,
                "stopTime":null
            },
            {
                "firstCD":20,
                "firstCDNum":[],
                "soldier":["zombie","axer"],
                "soldierCD":15,
                "groupCD":14,
                "groupCDRand":2,
                "groupTimes":0,
                "stopPos":null,
                "stopTime":null
            },
            {
                "firstCD":50,
                "firstCDNum":[],
                "soldier":["skeleton"],
                "soldierCD":0,
                "groupCD":20,
                "groupCDRand":4,
                "groupTimes":0,
                "stopPos":500,
                "stopTime":10
            }
        ],"banCard":[],"chosenCard":["shoveler","projector","regeneration","shielder",null,null]
    },
    {
        "set":{"levelType":"normal","attackTime":0,"baseMonsterHealth":10,"baseVillageHealth":10,
        "thunderTime":0,"thunderTimeRand":0,
        "iceTime":36,"iceTimeRand":4},
        "groups":[
            {
                "firstCD":0.8,
                "firstCDNum":[],
                "soldier":["spider","creeper","axer","skeleton"],
                "soldierCD":3,
                "groupCD":4,
                "groupCDRand":1,
                "groupTimes":0,
                "stopPos":null,
                "stopTime":null
            },
            {
                "firstCD":14,
                "firstCDNum":[],
                "soldier":["spider","axer"],
                "soldierCD":10,
                "groupCD":10,
                "groupCDRand":1,
                "groupTimes":0,
                "stopPos":null,
                "stopTime":null
            },
            {
                "firstCD":45,
                "firstCDNum":[],
                "soldier":["skeleton"],
                "soldierCD":22,
                "groupCD":22,
                "groupCDRand":2,
                "groupTimes":0,
                "stopPos":400,
                "stopTime":10
            },
            {
                "firstCD":70,
                "firstCDNum":[],
                "soldier":["creeper","spider","spider","axer","skeleton","skeleton"],
                "soldierCD":0,
                "groupCD":60,
                "groupCDRand":5,
                "groupTimes":0,
                "stopPos":null,
                "stopTime":null
            }

        ],"banCard":[],"chosenCard":["shoveler","projector","regeneration","shielder","assassinFirst",null]
    },
    {
        "set":{"levelType":"defence","attackTime":200,"baseMonsterHealth":20,"baseVillageHealth":20,
        "thunderTime":0,"thunderTimeRand":0,
        "iceTime":0,"iceTimeRand":4},
        "groups":[
            {
                "firstCD":5,
                "firstCDNum":[],
                "soldier":["zombie"],
                "soldierCD":0,
                "groupCD":10,
                "groupCDRand":2,
                "groupTimes":4,
                "stopPos":null,
                "stopTime":null
            },
            {
                "firstCD":7,
                "firstCDNum":[],
                "soldier":["axer"],
                "soldierCD":0,
                "groupCD":9,
                "groupCDRand":1,
                "groupTimes":3,
                "stopPos":null,
                "stopTime":null
            },
            {
                "firstCD":0.8,
                "firstCDNum":[],
                "soldier":["creeper","zombie","zombie","zombie"],
                "soldierCD":1.7,
                "groupCD":3,
                "groupCDRand":2,
                "groupTimes":4,
                "stopPos":null,
                "stopTime":null
            },
            {
                "firstCD":0,
                "firstCDNum":[3,3],
                "soldier":["creeper","zombie","zombie","zombie","axer","axer"],
                "soldierCD":1,
                "groupCD":0,
                "groupCDRand":0,
                "groupTimes":1,
                "stopPos":null,
                "stopTime":null
            }
        ],"banCard":[],"chosenCard":["shoveler","projector","regeneration","shielder","assassinFirst","snowman"]
    },
    {
        "set":{"levelType":"defence","attackTime":0,"baseMonsterHealth":20,"baseVillageHealth":20,
        "thunderTime":0,"thunderTimeRand":0,
        "iceTime":26,"iceTimeRand":3},
        "groups":[
            {
                "firstCD":0,
                "firstCDNum":[],
                "soldier":["zombie","axer","skeleton"],
                "soldierCD":3,
                "groupCD":4,
                "groupCDRand":1,
                "groupTimes":3,
                "stopPos":null,
                "stopTime":null
            },
            {
                "firstCD":10,
                "firstCDNum":[],
                "soldier":["witch","end"],
                "soldierCD":5,
                "groupCD":6,
                "groupCDRand":2,
                "groupTimes":3,
                "stopPos":null,
                "stopTime":null
            },
            {
                "firstCD":4,
                "firstCDNum":[2,2],
                "soldier":["zombie","zombie","axer","end","skeleton","witch"],
                "soldierCD":1,
                "groupCD":1,
                "groupCDRand":0,
                "groupTimes":1,
                "stopPos":null,
                "stopTime":null
            },
            {
                "firstCD":3,
                "firstCDNum":[2,3],
                "soldier":["zombie","axer","witch"],
                "soldierCD":1,
                "groupCD":6,
                "groupCDRand":0,
                "groupTimes":3,
                "stopPos":null,
                "stopTime":null
            },
            {
                "firstCD":8,
                "firstCDNum":[2,3],
                "soldier":["end","skeleton"],
                "soldierCD":5,
                "groupCD":6,
                "groupCDRand":2,
                "groupTimes":3,
                "stopPos":null,
                "stopTime":null
            },
            {
                "firstCD":0,
                "firstCDNum":[2,5],
                "soldier":["zombie","zombie","zombie","axer","end","end","skeleton","witch"],
                "soldierCD":1,
                "groupCD":1,
                "groupCDRand":0,
                "groupTimes":1,
                "stopPos":null,
                "stopTime":null
            }
        ],"banCard":[],"chosenCard":[]
    },
    {
        "set":{"levelType":"normal","attackTime":0,"baseMonsterHealth":20,"baseVillageHealth":20,
        "thunderTime":0,"thunderTimeRand":0,
        "iceTime":0,"iceTimeRand":0},
        "groups":[
            {
                "firstCD":0,
                "firstCDNum":[],
                "soldier":["zombie"],
                "soldierCD":3,
                "groupCD":3,
                "groupCDRand":1,
                "groupTimes":1,
                "stopPos":null,
                "stopTime":null
            }
        ],"banCard":[],"chosenCard":["shoveler","assassinFirst","power","regeneration","shoveler","iron"]
    },
    {
        "set":{"levelType":"boss","attackTime":0,"baseMonsterHealth":10,"baseVillageHealth":10,
        "thunderTime":2,"thunderTimeRand":0,
        "iceTime":0,"iceTimeRand":0},
        "groups":[
            {
                "firstCD":0,
                "firstCDNum":[],
                "soldier":["zombie"],
                "soldierCD":3,
                "groupCD":2,
                "groupCDRand":0,
                "groupTimes":1,
                "stopPos":null,
                "stopTime":null
            }
        ],"banCard":[],"chosenCard":["shoveler","projector","projector","assassinFirst","snowman","flyer"]
    },
    {
        "set":{"levelType":"normal","attackTime":0,"baseMonsterHealth":10,"baseVillageHealth":10,
        "thunderTime":0 ,"thunderTimeRand":0,
        "iceTime":0,"iceTimeRand":0},
        "groups":[
            {
                "firstCD":0,
                "soldier":["zombie"],
                "firstCDNum":[],
                "soldierCD":8,
                "groupCD":3,
                "groupCDRand":0,
                "groupTimes":1,
                "stopPos":null,
                "stopTime":null
            }
        ],"banCard":[],"chosenCard":[]
    },
    {
        "set":{"levelType":"attack","attackTime":300,"baseMonsterHealth":10,"baseVillageHealth":10,
        "thunderTime":2,"thunderTimeRand":0,
        "iceTime":0,"iceTimeRand":0},
        "groups":[
            {
                "firstCD":0,
                "soldier":["zombie"],
                "firstCDNum":[],
                "soldierCD":0.8,
                "groupCD":8,
                "groupCDRand":0,
                "groupTimes":1,
                "stopPos":null,
                "stopTime":null
            }
        ],"banCard":[],"chosenCard":[]
    }
]


